maximum_continual/__init__.py
maximum_continual/_function_type_hints_utils.py
maximum_continual/agent.py
maximum_continual/agent_types.py
maximum_continual/base_tools.py
maximum_continual/client.py
maximum_continual/local_python_executor.py
maximum_continual/shared_records.py
maximum_continual/system_prompt.py
maximum_continual/tool_validation.py
maximum_continual/tools.py
maximum_continual/types.py
maximum_continual/utils.py
maximum_continual/backend/__init__.py
maximum_continual/backend/abstract.py
maximum_continual/backend/modal_backend.py
maximum_continual/backend/modal_functions.py
maximum_continual/backend/notes_on_how_the_lora_path_works.md
maximum_continual/backend/vllm_backend.py
maximum_continual/tests/__init__.py
maximum_continual/tests/test_agent.py
maximum_continual/tests/test_client.py
maximum_continual/tests/test_types.py
maximum_continual-0.1.7.dist-info/METADATA
maximum_continual-0.1.7.dist-info/WHEEL
maximum_continual-0.1.7.dist-info/RECORD
