Metadata-Version: 2.4
Name: maximum-continual
Version: 0.1.7
Summary: A clean API for continual learning with LoRA models using reward-based feedback
Author: Maximum Continual Training
Requires-Python: <3.13,>=3.12
Requires-Dist: fastapi<0.116.0,>=0.115.12
Requires-Dist: litellm<2.0.0,>=1.55.0
Requires-Dist: modal>=0.63.0
Requires-Dist: pydantic<3.0.0,>=2.11.3
Requires-Dist: requests<3.0.0,>=2.32.3
Requires-Dist: smolagents<2.0.0,>=1.14.0
Requires-Dist: uvicorn<0.35.0,>=0.34.2
Provides-Extra: dev
Requires-Dist: black>=23.0.0; extra == 'dev'
Requires-Dist: mypy>=1.7.0; extra == 'dev'
Requires-Dist: pytest-cov>=4.1.0; extra == 'dev'
Requires-Dist: pytest>=7.4.0; extra == 'dev'
Requires-Dist: ruff>=0.1.0; extra == 'dev'
